simflux/__init__.py
simflux/simflux.py
simflux-0.1.1.dist-info/licenses/LICENCE
simflux-0.1.1.dist-info/METADATA
simflux-0.1.1.dist-info/WHEEL
simflux-0.1.1.dist-info/top_level.txt
simflux-0.1.1.dist-info/RECORD
