Metadata-Version: 2.4
Name: simflux
Version: 0.1.1
Summary: MINFLUX-like simulator
Author: Jack Peyton
License: MIT
Requires-Python: >=3.9
License-File: LICENCE
Requires-Dist: numpy>=1.23
Requires-Dist: pandas>=1.5
Requires-Dist: plotly>=5.0
Requires-Dist: h5py>=3.7
Provides-Extra: dev
Requires-Dist: pytest>=7; extra == "dev"
Dynamic: license-file
